dewloosh/math/__init__.py
dewloosh/math/array.py
dewloosh/math/arraysetops.py
dewloosh/math/hist.py
dewloosh/math/numint.py
dewloosh/math/function/__init__.py
dewloosh/math/function/constraint.py
dewloosh/math/function/function.py
dewloosh/math/function/functions.py
dewloosh/math/function/meta.py
dewloosh/math/function/relation.py
dewloosh/math/function/testfunction.py
dewloosh/math/linalg/__init__.py
dewloosh/math/linalg/_solve.py
dewloosh/math/linalg/_tensop.py
dewloosh/math/linalg/array.py
dewloosh/math/linalg/csys.py
dewloosh/math/linalg/frame.py
dewloosh/math/linalg/linalg.py
dewloosh/math/linalg/tensor.py
dewloosh/math/linalg/tensor3333.py
dewloosh/math/linalg/vector.py
dewloosh/math/linalg/frame/__init__.py
dewloosh/math/linalg/frame/frame.py
dewloosh/math/linalg/frontal/__init__.py
dewloosh/math/linalg/frontal/frontal.py
dewloosh/math/linalg/frontal/frutils.py
dewloosh/math/linalg/frontal/path.py
dewloosh/math/linalg/frontal/postproc.py
dewloosh/math/linalg/frontal/proc.py
dewloosh/math/linalg/frontal/topo.py
dewloosh/math/linalg/sparse/csr.py
dewloosh/math/linalg/sparse/graph.py
dewloosh/math/linalg/sparse/jaggedarray.py
dewloosh/math/linalg/sparse/utils.py
dewloosh/math/optimize/__init__.py
dewloosh/math/optimize/genetic.py
dewloosh/math/optimize/lp.py
dewloosh.math-0.0.dev8.dist-info/LICENSE
dewloosh.math-0.0.dev8.dist-info/METADATA
dewloosh.math-0.0.dev8.dist-info/WHEEL
dewloosh.math-0.0.dev8.dist-info/top_level.txt
dewloosh.math-0.0.dev8.dist-info/RECORD
