Metadata-Version: 2.1
Name: dewloosh.math
Version: 0.0.dev8
Summary: A math library for numerical calculations.
Home-page: https://github.com/dewloosh/dewloosh-math
Author: dewloosh
Author-email: dewloosh@gmail.com
License: UNKNOWN
Download-URL: https://github.com/dewloosh/dewloosh-math/archive/refs/tags/0.0.dev8.zip
Platform: UNKNOWN
Classifier: Development Status :: 3 - Alpha
Classifier: License :: OSI Approved :: MIT License
Classifier: Programming Language :: Python :: 3
Classifier: Operating System :: OS Independent
Requires-Python: >=3.6
Requires-Dist: dewloosh.core
Requires-Dist: scipy
Requires-Dist: awkward
Requires-Dist: networkx
Requires-Dist: sympy
